gmsdk/__init__.py
gmsdk/client.py
gmsdk/config.py
gmsdk/models/__init__.py
gmsdk/models/exceptions.py
gmsdk/models/types.py
gmsdk/proto/__init__.py
gmsdk/proto/gm_service_pb2.py
gmsdk/proto/gm_service_pb2_grpc.py
gmsdk/serializers/__init__.py
gmsdk/utils/__init__.py
gmsdk/utils/logging.py
quant_gmsdk-1.0.4.dist-info/licenses/LICENSE
quant_gmsdk-1.0.4.dist-info/METADATA
quant_gmsdk-1.0.4.dist-info/WHEEL
quant_gmsdk-1.0.4.dist-info/top_level.txt
quant_gmsdk-1.0.4.dist-info/RECORD
